igua-0.1.0.post1.dist-info/METADATA
igua-0.1.0.post1.dist-info/RECORD
igua-0.1.0.post1.dist-info/entry_points.txt
igua-0.1.0.post1.dist-info/WHEEL
igua-0.1.0.post1.dist-info/licenses/COPYING
igua/seqio.py
igua/cli.py
igua/hca.cpython-311-x86_64-linux-gnu.so
igua/mmseqs.py
igua/__main__.py
igua/__init__.py
igua/hca/lib.rs
igua/hca/distance.rs
igua/hca/clustering.rs
