Metadata-Version: 2.4
Name: igua
Version: 0.1.0.post1
Classifier: Development Status :: 4 - Beta
Classifier: Intended Audience :: Developers
Classifier: Intended Audience :: Science/Research
Classifier: License :: OSI Approved :: GNU General Public License v3 or later (GPLv3+)
Classifier: Operating System :: OS Independent
Classifier: Programming Language :: Rust
Classifier: Programming Language :: Python :: 3.7
Classifier: Programming Language :: Python :: 3.8
Classifier: Programming Language :: Python :: 3.9
Classifier: Programming Language :: Python :: 3.10
Classifier: Programming Language :: Python :: 3.11
Classifier: Programming Language :: Python :: 3.12
Classifier: Programming Language :: Python :: 3.13
Classifier: Programming Language :: Python :: Implementation :: CPython
Classifier: Programming Language :: Python :: Implementation :: PyPy
Classifier: Topic :: Scientific/Engineering :: Bio-Informatics
Classifier: Topic :: Scientific/Engineering :: Medical Science Apps.
Classifier: Typing :: Typed
Requires-Dist: scipy~=1.4
Requires-Dist: gb-io~=0.3.0
Requires-Dist: rich>=12.6,<15.0
Requires-Dist: numpy>=1.0,<3.0
Requires-Dist: pandas>=1.3,<3.0
Requires-Dist: anndata>=0.8,<0.12
Requires-Dist: biopython~=1.79
License-File: COPYING
Summary: Iterative Gene clUster Analysis, a high-throughput method for gene cluster family identification.
Keywords: bioinformatics,clusters,gene,family
Author-email: Martin Larralde <martin.larralde@embl.de>
Requires-Python: >=3.7
Project-URL: Homepage, https://github.com/zellerlab/IGUA/
Project-URL: Bug Tracker, https://github.com/zellerlab/IGUA/issues
Project-URL: Changelog, https://github.com/zellerlab/IGUA/blob/master/CHANGELOG.md
Project-URL: Builds, https://github.com/zellerlab/IGUA/actions/
Project-URL: PyPI, https://pypi.org/project/IGUA
